{
    "imageArr": [
        {
            "id": "1",
            "image_url": "https://img.zcool.cn/community/013de756fb63036ac7257948747896.jpg",
            "title": "爱美，人皆有之。"
        },
        {
            "id": "2",
            "image_url": "https://img.zcool.cn/community/01639a56fb62ff6ac725794891960d.jpg",
            "title": "摄品纷呈,影立人生。"
        },
        {
            "id": "3",
            "image_url": "https://img.zcool.cn/community/01270156fb62fd6ac72579485aa893.jpg",
            "title": "用光影分享爱的喜悦——魅影。"
        },
        {
            "id": "4",
            "image_url": "https://img.zcool.cn/community/01233056fb62fe32f875a9447400e1.jpg",
            "title": "摄品万千,影立今生。"
        }
    ],
    "list_data": [
        {
            "id": "1",
            "name": "小陈",
            "head_url": "http://114.55.249.135:8888/touxiang/a.png",
            "image_url": "https://img.zcool.cn/community/01233056fb62fe32f875a9447400e1.jpg",
            "title": "月初无限眷恋，月落转瞬千年。",
            "content": "月初无限眷恋，月落转瞬千年。月初无限眷恋，月落转瞬千年。月初无限眷恋，月落转瞬千年。月初无限眷恋，月落转瞬千年。",
            "extra": [{"label": "手机拍摄"},{"label": "风光"},{"label": "天天拍摄"},{"label": "旅行"},{"label": "求点评"}]
        },
        {
            "id": "2",
            "name": "小林",
            "head_url": "http://114.55.249.135:8888/touxiang/a.png",
            "image_url": "https://img.zcool.cn/community/01270156fb62fd6ac72579485aa893.jpg",
            "title": "月初无限眷恋，月落转瞬千年。",
            "content": "月初无限眷恋，月落转瞬千年。月初无限眷恋，月落转瞬千年。月初无限眷恋，月落转瞬千年。月初无限眷恋，月落转瞬千年。",
            "extra": [{"label": "手机拍摄"},{"label": "风光"},{"label": "天天拍摄"},{"label": "旅行"},{"label": "求点评"}]
        },
        {
            "id": "3",
            "name": "小陈",
            "head_url": "http://114.55.249.135:8888/touxiang/a.png",
            "image_url": "https://img.zcool.cn/community/01639a56fb62ff6ac725794891960d.jpg",
            "title": "月初无限眷恋，月落转瞬千年。",
            "content": "月初无限眷恋，月落转瞬千年。月初无限眷恋，月落转瞬千年。月初无限眷恋，月落转瞬千年。月初无限眷恋，月落转瞬千年。",
            "extra": [{"label": "手机拍摄"},{"label": "风光"},{"label": "天天拍摄"},{"label": "旅行"},{"label": "求点评"}]
        },
        {
            "id": "4",
            "name": "小林",
            "head_url": "http://114.55.249.135:8888/touxiang/a.png",
            "image_url": "https://img.zcool.cn/community/013de756fb63036ac7257948747896.jpg",
            "title": "月初无限眷恋，月落转瞬千年。",
            "content": "月初无限眷恋，月落转瞬千年。月初无限眷恋，月落转瞬千年。月初无限眷恋，月落转瞬千年。月初无限眷恋，月落转瞬千年。",
            "extra": [{"label": "手机拍摄"},{"label": "风光"},{"label": "天天拍摄"},{"label": "旅行"},{"label": "求点评"}]
        }
    ]
}